pyls_black_macchiato/__init__.py
pyls_black_macchiato/lsp.py
pyls_black_macchiato/plugin.py
pyls_black_macchiato-0.1.3.dist-info/LICENSE
pyls_black_macchiato-0.1.3.dist-info/METADATA
pyls_black_macchiato-0.1.3.dist-info/WHEEL
pyls_black_macchiato-0.1.3.dist-info/entry_points.txt
pyls_black_macchiato-0.1.3.dist-info/top_level.txt
pyls_black_macchiato-0.1.3.dist-info/RECORD
