Metadata-Version: 2.1
Name: pyls-black-macchiato
Version: 0.1.3
Summary: Black-macchiato plugin for the Python Language Server
Home-page: https://github.com/alex-lee/pyls-black-macchiato
Author: Alex Lee
Author-email: alex@collat.io
License: UNKNOWN
Platform: UNKNOWN
Classifier: Programming Language :: Python :: 3
Classifier: License :: OSI Approved :: MIT License
Classifier: Operating System :: OS Independent
Requires-Python: >=3.6.2
Requires-Dist: black (>=20.8b1)
Requires-Dist: black-macchiato (>=1.3.0)
Requires-Dist: python-language-server
Requires-Dist: typing-extensions
Requires-Dist: dataclasses (>=0.6) ; python_version < "3.7"
Provides-Extra: dev
Requires-Dist: flake8 ; extra == 'dev'
Requires-Dist: mypy ; extra == 'dev'
Requires-Dist: pytest ; extra == 'dev'
